LICENSE
MANIFEST.in
README.md
package.json
setup.py
mobile_dropdown/MobileDropdown.py
mobile_dropdown/__init__.py
mobile_dropdown/_imports_.py
mobile_dropdown/metadata.json
mobile_dropdown/mobile_dropdown.min.js
mobile_dropdown/mobile_dropdown.min.js.map
mobile_dropdown/package-info.json
mobile_dropdown.egg-info/PKG-INFO
mobile_dropdown.egg-info/SOURCES.txt
mobile_dropdown.egg-info/dependency_links.txt
mobile_dropdown.egg-info/top_level.txt