Metadata-Version: 2.1
Name: mobile-dropdown
Version: 1.2.9
Summary: Dash Mobile Dropdown Component
Author: s_matsumoto <s_matsumoto@thinkup-sol.co.jp>
License: MIT
Classifier: Framework :: Dash
License-File: LICENSE
